Metadata-Version: 2.1
Name: SQLibEngine
Version: 0.2.3
Summary: A simple SQLite3 wrapper for Python
Home-page: https://github.com/TRC-Loop/SQLib
Author: AK
Author-email: ak@stellar-code.com
License: UNKNOWN
Platform: UNKNOWN
Classifier: Programming Language :: Python :: 3
Classifier: License :: OSI Approved :: MIT License
Classifier: Operating System :: OS Independent
Requires-Python: >=3.6
License-File: LICENSE
